{"2019-01-01": {"frequencies": ["none", "none"], "statistics": {"mean": [-1, -1], "mode": [-1, -1], "median": [-1, -1], "variance": [-1, -1], "n_tot": [4704, 4704], "non_zeroes": [0, 0], "zeroes": [4704, 4704]}, "box_plot": {"min": [-1, -1], "quartile_010": [-1, -1], "quartile_025": [-1, -1], "median": [-1, -1], "quartile_075": [-1, -1], "quartile_090": [-1, -1], "max": [-1, -1]}}, "2019-01-07": {"frequencies": ["none", "none"], "statistics": {"mean": [-1, -1], "mode": [-1, -1], "median": [-1, -1], "variance": [-1, -1], "n_tot": [5488, 5488], "non_zeroes": [0, 0], "zeroes": [5488, 5488]}, "box_plot": {"min": [-1, -1], "quartile_010": [-1, -1], "quartile_025": [-1, -1], "median": [-1, -1], "quartile_075": [-1, -1], "quartile_090": [-1, -1], "max": [-1, -1]}}, "2019-01-14": {"frequencies": ["none", "none"], "statistics": {"mean": [-1, -1], "mode": [-1, -1], "median": [-1, -1], "variance": [-1, -1], "n_tot": [5488, 5488], "non_zeroes": [0, 0], "zeroes": [5488, 5488]}, "box_plot": {"min": [-1, -1], "quartile_010": [-1, -1], "quartile_025": [-1, -1], "median": [-1, -1], "quartile_075": [-1, -1], "quartile_090": [-1, -1], "max": [-1, -1]}}, "2019-01-21": {"frequencies": ["none", "none"], "statistics": {"mean": [-1, -1], "mode": [-1, -1], "median": [-1, -1], "variance": [-1, -1], "n_tot": [5488, 5488], "non_zeroes": [0, 0], "zeroes": [5488, 5488]}, "box_plot": {"min": [-1, -1], "quartile_010": [-1, -1], "quartile_025": [-1, -1], "median": [-1, -1], "quartile_075": [-1, -1], "quartile_090": [-1, -1], "max": [-1, -1]}}, "2019-01-28": {"frequencies": ["none", "none"], "statistics": {"mean": [-1, -1], "mode": [-1, -1], "median": [-1, -1], "variance": [-1, -1], "n_tot": [5488, 5488], "non_zeroes": [0, 0], "zeroes": [5488, 5488]}, "box_plot": {"min": [-1, -1], "quartile_010": [-1, -1], "quartile_025": [-1, -1], "median": [-1, -1], "quartile_075": [-1, -1], "quartile_090": [-1, -1], "max": [-1, -1]}}, "2019-02-04": {"frequencies": ["none", "none"], "statistics": {"mean": [-1, -1], "mode": [-1, -1], "median": [-1, -1], "variance": [-1, -1], "n_tot": [5488, 5488], "non_zeroes": [0, 0], "zeroes": [5488, 5488]}, "box_plot": {"min": [-1, -1], "quartile_010": [-1, -1], "quartile_025": [-1, -1], "median": [-1, -1], "quartile_075": [-1, -1], "quartile_090": [-1, -1], "max": [-1, -1]}}, "2019-02-11": {"frequencies": ["none", "none"], "statistics": {"mean": [359.6500850340136, -1], "mode": [0, -1], "median": [0.0, -1], "variance": [2976716.1773798307, -1], "n_tot": [5488, 5488], "non_zeroes": [2352, 0], "zeroes": [3136, 5488]}, "box_plot": {"min": [0, -1], "quartile_010": [0, -1], "quartile_025": [0, -1], "median": [0.0, -1], "quartile_075": [0, -1], "quartile_090": [0, -1], "max": [10000, -1]}}, "2019-02-18": {"frequencies": ["none", "none"], "statistics": {"mean": [600.1948502556611, -1], "mode": [0, -1], "median": [0.0, -1], "variance": [4254350.090062973, -1], "n_tot": [5488, 5488], "non_zeroes": [5476, 0], "zeroes": [12, 5488]}, "box_plot": {"min": [0, -1], "quartile_010": [0, -1], "quartile_025": [0, -1], "median": [0.0, -1], "quartile_075": [0, -1], "quartile_090": [980, -1], "max": [10000, -1]}}, "2019-02-25": {"frequencies": ["none", "none"], "statistics": {"mean": [532.8394679300292, 445.88878676470586], "mode": [0, 0], "median": [0.0, 0.0], "variance": [2539706.6939258697, 846275.7291105782], "n_tot": [5488, 5488], "non_zeroes": [5488, 1088], "zeroes": [0, 4400]}, "box_plot": {"min": [0, 0], "quartile_010": [0, 0], "quartile_025": [0, 0], "median": [0.0, 0.0], "quartile_075": [0, 0], "quartile_090": [1960, 1960], "max": [10000, 4235]}}, "2019-03-04": {"frequencies": ["none", "none"], "statistics": {"mean": [427.32397959183675, 234.73254759746146], "mode": [0, 0], "median": [0.0, 0.0], "variance": [1933942.1286612514, 328692.47073365794], "n_tot": [5488, 5488], "non_zeroes": [5488, 4412], "zeroes": [0, 1076]}, "box_plot": {"min": [0, 0], "quartile_010": [0, 0], "quartile_025": [0, 0], "median": [0.0, 0.0], "quartile_075": [0, 0], "quartile_090": [1098, 980], "max": [10000, 5333]}}, "2019-03-11": {"frequencies": ["none", "none"], "statistics": {"mean": [503.0525085034014, 632.3930434782609], "mode": [0, 0], "median": [0.0, 0.0], "variance": [1634358.6570338933, 2090031.041621877], "n_tot": [5488, 5488], "non_zeroes": [4704, 2300], "zeroes": [784, 3188]}, "box_plot": {"min": [0, 0], "quartile_010": [0, 0], "quartile_025": [0, 0], "median": [0.0, 0.0], "quartile_075": [549, 705], "quartile_090": [1176, 1960], "max": [9607, 9607]}}, "2019-03-18": {"frequencies": ["none", "none"], "statistics": {"mean": [518.7456268221574, 378.9970178926441], "mode": [0, 0], "median": [78.0, 235.0], "variance": [1264337.6597220781, 186895.82188164545], "n_tot": [5488, 5488], "non_zeroes": [5488, 1006], "zeroes": [0, 4482]}, "box_plot": {"min": [0, 0], "quartile_010": [0, 0], "quartile_025": [0, 78], "median": [78.0, 235.0], "quartile_075": [549, 549], "quartile_090": [1215, 823], "max": [8078, 2078]}}, "2019-03-25": {"frequencies": ["none", "none"], "statistics": {"mean": [418.426749271137, 366.6901968998743], "mode": [0, 0], "median": [0.0, 39.0], "variance": [809792.5268002929, 469804.8273205981], "n_tot": [5488, 5488], "non_zeroes": [5488, 4774], "zeroes": [0, 714]}, "box_plot": {"min": [0, 0], "quartile_010": [0, 0], "quartile_025": [0, 0], "median": [0.0, 39.0], "quartile_075": [392, 392], "quartile_090": [1294, 1215], "max": [10000, 10000]}}, "2019-04-01": {"frequencies": ["none", "none"], "statistics": {"mean": [226.765543426673, 276.1626822157434], "mode": [0, 0], "median": [0.0, 0.0], "variance": [377782.0309415869, 444283.1225498173], "n_tot": [5488, 5488], "non_zeroes": [4214, 3430], "zeroes": [1274, 2058]}, "box_plot": {"min": [0, 0], "quartile_010": [0, 0], "quartile_025": [0, 0], "median": [0.0, 0.0], "quartile_075": [196, 313], "quartile_090": [666, 666], "max": [4823, 4823]}}, "2019-04-08": {"frequencies": ["none", "none"], "statistics": {"mean": [340.0255183413078, 409.85157824042983], "mode": [0, 0], "median": [0.0, 156.0], "variance": [440605.5909466204, 520393.9813226679], "n_tot": [5488, 5488], "non_zeroes": [3762, 2978], "zeroes": [1726, 2510]}, "box_plot": {"min": [0, 0], "quartile_010": [0, 0], "quartile_025": [0, 0], "median": [0.0, 156.0], "quartile_075": [431, 470], "quartile_090": [862, 1098], "max": [3490, 3490]}}, "2019-04-15": {"frequencies": ["none", "none"], "statistics": {"mean": [211.16938775510204, -1], "mode": [0, -1], "median": [0.0, -1], "variance": [1010738.2586186605, -1], "n_tot": [5488, 5488], "non_zeroes": [3920, 0], "zeroes": [1568, 5488]}, "box_plot": {"min": [0, -1], "quartile_010": [0, -1], "quartile_025": [0, -1], "median": [0.0, -1], "quartile_075": [0, -1], "quartile_090": [0, -1], "max": [8274, -1]}}, "2019-04-22": {"frequencies": ["none", "none"], "statistics": {"mean": [214.40391156462584, 269.8737244897959], "mode": [0, 0], "median": [0.0, 0.0], "variance": [622999.6480051089, 601216.3643889274], "n_tot": [5488, 5488], "non_zeroes": [4704, 1568], "zeroes": [784, 3920]}, "box_plot": {"min": [0, 0], "quartile_010": [0, 0], "quartile_025": [0, 0], "median": [0.0, 0.0], "quartile_075": [0, 235], "quartile_090": [509, 666], "max": [10000, 3921]}}, "2019-04-29": {"frequencies": ["none", "none"], "statistics": {"mean": [606.092899659864, 612.9224388220655], "mode": [0, 0], "median": [0.0, 0], "variance": [1863012.5018930149, 1282023.560371809], "n_tot": [5488, 5488], "non_zeroes": [4704, 2411], "zeroes": [784, 3077]}, "box_plot": {"min": [0, 0], "quartile_010": [0, 0], "quartile_025": [0, 0], "median": [0.0, 0], "quartile_075": [784, 1019], "quartile_090": [2156, 2000], "max": [10000, 6509]}}, "2019-05-06": {"frequencies": ["none", "none"], "statistics": {"mean": [291.27277696793004, 235.625], "mode": [0, 0], "median": [0.0, 0.0], "variance": [423876.1754424784, 185585.11483253588], "n_tot": [5488, 5488], "non_zeroes": [5488, 3136], "zeroes": [0, 2352]}, "box_plot": {"min": [0, 0], "quartile_010": [0, 0], "quartile_025": [0, 0], "median": [0.0, 0.0], "quartile_075": [235, 392], "quartile_090": [980, 745], "max": [4666, 3686]}}, "2019-05-13": {"frequencies": ["none", "none"], "statistics": {"mean": [240.87536443148687, 301.03156565656565], "mode": [0, 0], "median": [39.0, 0.0], "variance": [185237.98628563352, 279515.4882663477], "n_tot": [5488, 5488], "non_zeroes": [5488, 2376], "zeroes": [0, 3112]}, "box_plot": {"min": [0, 0], "quartile_010": [0, 0], "quartile_025": [0, 0], "median": [39.0, 0.0], "quartile_075": [352, 470], "quartile_090": [784, 823], "max": [3215, 3215]}}, "2019-05-20": {"frequencies": ["none", "none"], "statistics": {"mean": [304.661443148688, 509.88898678414097], "mode": [0, 0], "median": [0.0, 0.0], "variance": [389205.8569275324, 752933.9665159407], "n_tot": [5488, 5488], "non_zeroes": [5488, 2270], "zeroes": [0, 3218]}, "box_plot": {"min": [0, 0], "quartile_010": [0, 0], "quartile_025": [0, 0], "median": [0.0, 0.0], "quartile_075": [352, 431], "quartile_090": [980, 2039], "max": [4000, 4000]}}, "2019-05-27": {"frequencies": ["none", "none"], "statistics": {"mean": [311.12919096209913, 314.115649183147], "mode": [0, 0], "median": [196.0, 196.0], "variance": [156390.70082077783, 146172.20468402997], "n_tot": [5488, 5488], "non_zeroes": [5488, 2326], "zeroes": [0, 3162]}, "box_plot": {"min": [0, 0], "quartile_010": [0, 0], "quartile_025": [0, 0], "median": [196.0, 196.0], "quartile_075": [549, 470], "quartile_090": [901, 901], "max": [1764, 1450]}}, "2019-06-03": {"frequencies": ["none", "none"], "statistics": {"mean": [696.3128644314869, 855.0780876494024], "mode": [0, 0], "median": [97.5, 235.0], "variance": [1471265.2687828997, 1572611.0660401837], "n_tot": [5488, 5488], "non_zeroes": [5488, 2510], "zeroes": [0, 2978]}, "box_plot": {"min": [0, 0], "quartile_010": [0, 0], "quartile_025": [0, 0], "median": [97.5, 235.0], "quartile_075": [941, 1411], "quartile_090": [1960, 2274], "max": [6941, 6941]}}, "2019-06-10": {"frequencies": ["none", "none"], "statistics": {"mean": [969.7048104956268, 1013.6504030547306], "mode": [0, 0], "median": [156.0, 39], "variance": [2229822.049898488, 3138178.6816350245], "n_tot": [5488, 5488], "non_zeroes": [5488, 2357], "zeroes": [0, 3131]}, "box_plot": {"min": [0, 0], "quartile_010": [0, 0], "quartile_025": [0, 0], "median": [156.0, 39], "quartile_075": [1372, 1294], "quartile_090": [3411, 3411], "max": [7176, 7176]}}, "2019-06-17": {"frequencies": ["none", "none"], "statistics": {"mean": [909.5708819241983, 613.1528976572133], "mode": [0, 0], "median": [0.0, 0.0], "variance": [2724991.748574254, 888091.5867250962], "n_tot": [5488, 5488], "non_zeroes": [5488, 1622], "zeroes": [0, 3866]}, "box_plot": {"min": [0, 0], "quartile_010": [0, 0], "quartile_025": [0, 0], "median": [0.0, 0.0], "quartile_075": [1372, 1254], "quartile_090": [2509, 1960], "max": [10000, 3803]}}, "2019-06-24": {"frequencies": ["none", "none"], "statistics": {"mean": [1008.6869533527697, 951.7022538552787], "mode": [0, 0], "median": [0.0, 0.0], "variance": [4785609.022085996, 3392259.577763463], "n_tot": [5488, 5488], "non_zeroes": [5488, 1686], "zeroes": [0, 3802]}, "box_plot": {"min": [0, 0], "quartile_010": [0, 0], "quartile_025": [0, 0], "median": [0.0, 0.0], "quartile_075": [745, 941], "quartile_090": [3607, 2588], "max": [10000, 10000]}}, "2019-07-01": {"frequencies": ["none", "none"], "statistics": {"mean": [245.49945335276968, 234.41666666666666], "mode": [0, 0], "median": [0.0, 0.0], "variance": [137180.3860029816, 150661.86718888298], "n_tot": [5488, 5488], "non_zeroes": [5488, 1884], "zeroes": [0, 3604]}, "box_plot": {"min": [0, 0], "quartile_010": [0, 0], "quartile_025": [0, 0], "median": [0.0, 0.0], "quartile_075": [392, 274], "quartile_090": [784, 784], "max": [1764, 1529]}}, "2019-07-08": {"frequencies": ["none", "none"], "statistics": {"mean": [309.8401967930029, 417.2068965517241], "mode": [0, 0], "median": [0.0, 0], "variance": [315985.0644892633, 702993.9841565704], "n_tot": [5488, 5488], "non_zeroes": [5488, 667], "zeroes": [0, 4821]}, "box_plot": {"min": [0, 0], "quartile_010": [0, 0], "quartile_025": [0, 0], "median": [0.0, 0], "quartile_075": [352, 274], "quartile_090": [1058, 1686], "max": [3568, 3568]}}, "2019-07-15": {"frequencies": ["none", "none"], "statistics": {"mean": [133.72430758017492, 207.72704081632654], "mode": [0, 0], "median": [0.0, 0.0], "variance": [54277.35190037704, 80369.31237130868], "n_tot": [5488, 5488], "non_zeroes": [5488, 784], "zeroes": [0, 4704]}, "box_plot": {"min": [0, 0], "quartile_010": [0, 0], "quartile_025": [0, 0], "median": [0.0, 0.0], "quartile_075": [235, 352], "quartile_090": [470, 627], "max": [1450, 1098]}}, "2019-07-22": {"frequencies": ["none", "none"], "statistics": {"mean": [500.714832361516, -1], "mode": [0, -1], "median": [0.0, -1], "variance": [1548119.6385479579, -1], "n_tot": [5488, 5488], "non_zeroes": [5488, 0], "zeroes": [0, 5488]}, "box_plot": {"min": [0, -1], "quartile_010": [0, -1], "quartile_025": [0, -1], "median": [0.0, -1], "quartile_075": [392, -1], "quartile_090": [1294, -1], "max": [9725, -1]}}, "2019-07-29": {"frequencies": ["none", "none"], "statistics": {"mean": [419.01712827988337, 515.2886904761905], "mode": [0, 0], "median": [0.0, 0.0], "variance": [617101.6793129109, 906941.9277916601], "n_tot": [5488, 5488], "non_zeroes": [5488, 2688], "zeroes": [0, 2800]}, "box_plot": {"min": [0, 0], "quartile_010": [0, 0], "quartile_025": [0, 0], "median": [0.0, 0.0], "quartile_075": [549, 745], "quartile_090": [1647, 2000], "max": [4274, 4274]}}, "2019-08-05": {"frequencies": ["none", "none"], "statistics": {"mean": [1811.7372448979593, 1506.091743119266], "mode": [0, 0], "median": [0.0, 0], "variance": [8654301.271205967, 4015890.74751818], "n_tot": [5488, 5488], "non_zeroes": [5488, 1853], "zeroes": [0, 3635]}, "box_plot": {"min": [0, 0], "quartile_010": [0, 0], "quartile_025": [0, 0], "median": [0.0, 0], "quartile_075": [2784, 3411], "quartile_090": [7372, 4196], "max": [10000, 8509]}}, "2019-08-12": {"frequencies": ["none", "none"], "statistics": {"mean": [1090.2895408163265, 616.2946428571429], "mode": [0, 0], "median": [0.0, 392.0], "variance": [6656251.777823883, 763382.7674808428], "n_tot": [5488, 5488], "non_zeroes": [5488, 784], "zeroes": [0, 4704]}, "box_plot": {"min": [0, 0], "quartile_010": [0, 0], "quartile_025": [0, 0], "median": [0.0, 392.0], "quartile_075": [745, 1058], "quartile_090": [3058, 1529], "max": [10000, 3176]}}, "2019-08-19": {"frequencies": ["none", "none"], "statistics": {"mean": [268.74763533910243, 83.53700516351118], "mode": [0, 0], "median": [0, 0], "variance": [314016.8577968428, 27373.221473084453], "n_tot": [5488, 5488], "non_zeroes": [4969, 581], "zeroes": [519, 4907]}, "box_plot": {"min": [0, 0], "quartile_010": [0, 0], "quartile_025": [0, 0], "median": [0, 0], "quartile_075": [117, 78], "quartile_090": [1215, 196], "max": [5019, 588]}}, "2019-08-26": {"frequencies": ["none", "none"], "statistics": {"mean": [1008.4016034985423, 373.006908462867], "mode": [0, 0], "median": [196.0, 274], "variance": [3475895.913407306, 136130.79257897378], "n_tot": [5488, 5488], "non_zeroes": [5488, 1737], "zeroes": [0, 3751]}, "box_plot": {"min": [0, 0], "quartile_010": [0, 0], "quartile_025": [0, 0], "median": [196.0, 274], "quartile_075": [1098, 666], "quartile_090": [3294, 901], "max": [10000, 1294]}}, "2019-09-02": {"frequencies": ["none", "none"], "statistics": {"mean": [164.2365160349854, 179.77126099706746], "mode": [0, 0], "median": [0.0, 0], "variance": [93292.30526739321, 119613.54111840084], "n_tot": [5488, 5488], "non_zeroes": [5488, 2387], "zeroes": [0, 3101]}, "box_plot": {"min": [0, 0], "quartile_010": [0, 0], "quartile_025": [0, 0], "median": [0.0, 0], "quartile_075": [196, 235], "quartile_090": [509, 588], "max": [2823, 2823]}}, "2019-09-09": {"frequencies": ["none", "none"], "statistics": {"mean": [209.1503279883382, 179.51115660184237], "mode": [0, 0], "median": [0.0, 0], "variance": [158972.9431345744, 107275.60004954242], "n_tot": [5488, 5488], "non_zeroes": [5488, 4885], "zeroes": [0, 603]}, "box_plot": {"min": [0, 0], "quartile_010": [0, 0], "quartile_025": [0, 0], "median": [0.0, 0], "quartile_075": [313, 274], "quartile_090": [666, 588], "max": [3882, 2627]}}, "2019-09-16": {"frequencies": ["none", "none"], "statistics": {"mean": [292.57142857142856, -1], "mode": [0, -1], "median": [39.0, -1], "variance": [203924.72717331877, -1], "n_tot": [5488, 5488], "non_zeroes": [5488, 0], "zeroes": [0, 5488]}, "box_plot": {"min": [0, -1], "quartile_010": [0, -1], "quartile_025": [0, -1], "median": [39.0, -1], "quartile_075": [392, -1], "quartile_090": [980, -1], "max": [2156, -1]}}, "2019-09-23": {"frequencies": ["none", "none"], "statistics": {"mean": [636.4190051020408, 346.11842105263156], "mode": [0, 0], "median": [39.0, 0.0], "variance": [1629580.3438530606, 331705.7352798222], "n_tot": [5488, 5488], "non_zeroes": [4704, 380], "zeroes": [784, 5108]}, "box_plot": {"min": [0, 0], "quartile_010": [0, 0], "quartile_025": [0, 0], "median": [39.0, 0.0], "quartile_075": [745, 745], "quartile_090": [1686, 1568], "max": [8901, 1568]}}, "2019-09-30": {"frequencies": ["none", "none"], "statistics": {"mean": [861.4916180758017, -1], "mode": [0, -1], "median": [0.0, -1], "variance": [2734416.2496107947, -1], "n_tot": [5488, 5488], "non_zeroes": [5488, 0], "zeroes": [0, 5488]}, "box_plot": {"min": [0, -1], "quartile_010": [0, -1], "quartile_025": [0, -1], "median": [0.0, -1], "quartile_075": [1137, -1], "quartile_090": [2823, -1], "max": [10000, -1]}}, "2019-10-07": {"frequencies": ["none", "none"], "statistics": {"mean": [869.2594752186588, 958.4666666666667], "mode": [0, 0], "median": [0.0, 78.0], "variance": [3564125.514581244, 2111683.5381794367], "n_tot": [5488, 5488], "non_zeroes": [5488, 510], "zeroes": [0, 4978]}, "box_plot": {"min": [0, 0], "quartile_010": [0, 0], "quartile_025": [0, 0], "median": [0.0, 78.0], "quartile_075": [705, 1529], "quartile_090": [3019, 3725], "max": [10000, 4313]}}, "2019-10-14": {"frequencies": ["none", "none"], "statistics": {"mean": [1691.5071064139943, -1], "mode": [0, -1], "median": [0.0, -1], "variance": [8488299.763025854, -1], "n_tot": [5488, 5488], "non_zeroes": [5488, 0], "zeroes": [0, 5488]}, "box_plot": {"min": [0, -1], "quartile_010": [0, -1], "quartile_025": [0, -1], "median": [0.0, -1], "quartile_075": [1843, -1], "quartile_090": [6039, -1], "max": [10000, -1]}}, "2019-10-21": {"frequencies": ["none", "none"], "statistics": {"mean": [588.9416058394161, -1], "mode": [0, -1], "median": [0, -1], "variance": [2413481.710239833, -1], "n_tot": [5488, 5488], "non_zeroes": [3151, 0], "zeroes": [2337, 5488]}, "box_plot": {"min": [0, -1], "quartile_010": [0, -1], "quartile_025": [0, -1], "median": [0, -1], "quartile_075": [470, -1], "quartile_090": [2156, -1], "max": [10000, -1]}}, "2019-10-28": {"frequencies": ["none", "none"], "statistics": {"mean": [-1, -1], "mode": [-1, -1], "median": [-1, -1], "variance": [-1, -1], "n_tot": [5488, 5488], "non_zeroes": [0, 0], "zeroes": [5488, 5488]}, "box_plot": {"min": [-1, -1], "quartile_010": [-1, -1], "quartile_025": [-1, -1], "median": [-1, -1], "quartile_075": [-1, -1], "quartile_090": [-1, -1], "max": [-1, -1]}}, "2019-11-04": {"frequencies": ["none", "none"], "statistics": {"mean": [-1, -1], "mode": [-1, -1], "median": [-1, -1], "variance": [-1, -1], "n_tot": [5488, 5488], "non_zeroes": [0, 0], "zeroes": [5488, 5488]}, "box_plot": {"min": [-1, -1], "quartile_010": [-1, -1], "quartile_025": [-1, -1], "median": [-1, -1], "quartile_075": [-1, -1], "quartile_090": [-1, -1], "max": [-1, -1]}}, "2019-11-11": {"frequencies": ["none", "none"], "statistics": {"mean": [-1, -1], "mode": [-1, -1], "median": [-1, -1], "variance": [-1, -1], "n_tot": [5488, 5488], "non_zeroes": [0, 0], "zeroes": [5488, 5488]}, "box_plot": {"min": [-1, -1], "quartile_010": [-1, -1], "quartile_025": [-1, -1], "median": [-1, -1], "quartile_075": [-1, -1], "quartile_090": [-1, -1], "max": [-1, -1]}}, "2019-11-18": {"frequencies": ["none", "none"], "statistics": {"mean": [-1, -1], "mode": [-1, -1], "median": [-1, -1], "variance": [-1, -1], "n_tot": [5488, 5488], "non_zeroes": [0, 0], "zeroes": [5488, 5488]}, "box_plot": {"min": [-1, -1], "quartile_010": [-1, -1], "quartile_025": [-1, -1], "median": [-1, -1], "quartile_075": [-1, -1], "quartile_090": [-1, -1], "max": [-1, -1]}}, "2019-11-25": {"frequencies": ["none", "none"], "statistics": {"mean": [-1, -1], "mode": [-1, -1], "median": [-1, -1], "variance": [-1, -1], "n_tot": [5488, 5488], "non_zeroes": [0, 0], "zeroes": [5488, 5488]}, "box_plot": {"min": [-1, -1], "quartile_010": [-1, -1], "quartile_025": [-1, -1], "median": [-1, -1], "quartile_075": [-1, -1], "quartile_090": [-1, -1], "max": [-1, -1]}}, "2019-12-02": {"frequencies": ["none", "none"], "statistics": {"mean": [-1, -1], "mode": [-1, -1], "median": [-1, -1], "variance": [-1, -1], "n_tot": [5488, 5488], "non_zeroes": [0, 0], "zeroes": [5488, 5488]}, "box_plot": {"min": [-1, -1], "quartile_010": [-1, -1], "quartile_025": [-1, -1], "median": [-1, -1], "quartile_075": [-1, -1], "quartile_090": [-1, -1], "max": [-1, -1]}}, "2019-12-09": {"frequencies": ["none", "none"], "statistics": {"mean": [-1, -1], "mode": [-1, -1], "median": [-1, -1], "variance": [-1, -1], "n_tot": [5488, 5488], "non_zeroes": [0, 0], "zeroes": [5488, 5488]}, "box_plot": {"min": [-1, -1], "quartile_010": [-1, -1], "quartile_025": [-1, -1], "median": [-1, -1], "quartile_075": [-1, -1], "quartile_090": [-1, -1], "max": [-1, -1]}}, "2019-12-16": {"frequencies": ["none", "none"], "statistics": {"mean": [-1, -1], "mode": [-1, -1], "median": [-1, -1], "variance": [-1, -1], "n_tot": [5488, 5488], "non_zeroes": [0, 0], "zeroes": [5488, 5488]}, "box_plot": {"min": [-1, -1], "quartile_010": [-1, -1], "quartile_025": [-1, -1], "median": [-1, -1], "quartile_075": [-1, -1], "quartile_090": [-1, -1], "max": [-1, -1]}}, "2019-12-23": {"frequencies": ["none", "none"], "statistics": {"mean": [-1, -1], "mode": [-1, -1], "median": [-1, -1], "variance": [-1, -1], "n_tot": [5488, 5488], "non_zeroes": [0, 0], "zeroes": [5488, 5488]}, "box_plot": {"min": [-1, -1], "quartile_010": [-1, -1], "quartile_025": [-1, -1], "median": [-1, -1], "quartile_075": [-1, -1], "quartile_090": [-1, -1], "max": [-1, -1]}}, "2019-12-30": {"frequencies": ["none", "none"], "statistics": {"mean": [-1, -1], "mode": [-1, -1], "median": [-1, -1], "variance": [-1, -1], "n_tot": [5488, 5488], "non_zeroes": [0, 0], "zeroes": [5488, 5488]}, "box_plot": {"min": [-1, -1], "quartile_010": [-1, -1], "quartile_025": [-1, -1], "median": [-1, -1], "quartile_075": [-1, -1], "quartile_090": [-1, -1], "max": [-1, -1]}}, "2020-01-06": {"frequencies": ["none", "none"], "statistics": {"mean": [-1, -1], "mode": [-1, -1], "median": [-1, -1], "variance": [-1, -1], "n_tot": [5488, 5488], "non_zeroes": [0, 0], "zeroes": [5488, 5488]}, "box_plot": {"min": [-1, -1], "quartile_010": [-1, -1], "quartile_025": [-1, -1], "median": [-1, -1], "quartile_075": [-1, -1], "quartile_090": [-1, -1], "max": [-1, -1]}}, "2020-01-13": {"frequencies": ["none", "none"], "statistics": {"mean": [-1, -1], "mode": [-1, -1], "median": [-1, -1], "variance": [-1, -1], "n_tot": [5488, 5488], "non_zeroes": [0, 0], "zeroes": [5488, 5488]}, "box_plot": {"min": [-1, -1], "quartile_010": [-1, -1], "quartile_025": [-1, -1], "median": [-1, -1], "quartile_075": [-1, -1], "quartile_090": [-1, -1], "max": [-1, -1]}}, "2020-01-20": {"frequencies": ["none", "none"], "statistics": {"mean": [-1, -1], "mode": [-1, -1], "median": [-1, -1], "variance": [-1, -1], "n_tot": [5488, 5488], "non_zeroes": [0, 0], "zeroes": [5488, 5488]}, "box_plot": {"min": [-1, -1], "quartile_010": [-1, -1], "quartile_025": [-1, -1], "median": [-1, -1], "quartile_075": [-1, -1], "quartile_090": [-1, -1], "max": [-1, -1]}}, "2020-01-27": {"frequencies": ["none", "none"], "statistics": {"mean": [-1, -1], "mode": [-1, -1], "median": [-1, -1], "variance": [-1, -1], "n_tot": [5488, 5488], "non_zeroes": [0, 0], "zeroes": [5488, 5488]}, "box_plot": {"min": [-1, -1], "quartile_010": [-1, -1], "quartile_025": [-1, -1], "median": [-1, -1], "quartile_075": [-1, -1], "quartile_090": [-1, -1], "max": [-1, -1]}}, "2020-02-03": {"frequencies": ["none", "none"], "statistics": {"mean": [-1, -1], "mode": [-1, -1], "median": [-1, -1], "variance": [-1, -1], "n_tot": [5488, 5488], "non_zeroes": [0, 0], "zeroes": [5488, 5488]}, "box_plot": {"min": [-1, -1], "quartile_010": [-1, -1], "quartile_025": [-1, -1], "median": [-1, -1], "quartile_075": [-1, -1], "quartile_090": [-1, -1], "max": [-1, -1]}}, "2020-02-10": {"frequencies": ["none", "none"], "statistics": {"mean": [678.2085696282294, -1], "mode": [0, -1], "median": [0, -1], "variance": [3751079.771729794, -1], "n_tot": [5488, 5488], "non_zeroes": [1587, 0], "zeroes": [3901, 5488]}, "box_plot": {"min": [0, -1], "quartile_010": [0, -1], "quartile_025": [0, -1], "median": [0, -1], "quartile_075": [0, -1], "quartile_090": [4313, -1], "max": [10000, -1]}}, "2020-02-17": {"frequencies": ["none", "none"], "statistics": {"mean": [937.9489795918367, -1], "mode": [0, -1], "median": [0.0, -1], "variance": [6118817.509197343, -1], "n_tot": [5488, 5488], "non_zeroes": [4704, 0], "zeroes": [784, 5488]}, "box_plot": {"min": [0, -1], "quartile_010": [0, -1], "quartile_025": [0, -1], "median": [0.0, -1], "quartile_075": [431, -1], "quartile_090": [2549, -1], "max": [10000, -1]}}, "2020-02-24": {"frequencies": ["none", "none"], "statistics": {"mean": [842.6122448979592, 183.49586776859505], "mode": [0, 431], "median": [0.0, 78], "variance": [4512322.730245516, 37534.2520661157], "n_tot": [5488, 5488], "non_zeroes": [5488, 121], "zeroes": [0, 5367]}, "box_plot": {"min": [0, 0], "quartile_010": [0, 0], "quartile_025": [0, 0], "median": [0.0, 78], "quartile_075": [509, 431], "quartile_090": [2235, 431], "max": [10000, 431]}}, "2020-03-02": {"frequencies": ["none", "none"], "statistics": {"mean": [545.5798104956268, 446.20297223308563], "mode": [0, 0], "median": [0.0, 0.0], "variance": [1916081.2500533995, 1137209.2930402546], "n_tot": [5488, 5488], "non_zeroes": [5488, 5114], "zeroes": [0, 374]}, "box_plot": {"min": [0, 0], "quartile_010": [0, 0], "quartile_025": [0, 0], "median": [0.0, 0.0], "quartile_075": [470, 431], "quartile_090": [1568, 980], "max": [10000, 7882]}}, "2020-03-09": {"frequencies": ["none", "none"], "statistics": {"mean": [868.0430029154519, 968.0624567872782], "mode": [0, 0], "median": [0.0, 0], "variance": [3085505.253481194, 3420714.795775521], "n_tot": [5488, 5488], "non_zeroes": [5488, 4339], "zeroes": [0, 1149]}, "box_plot": {"min": [0, 0], "quartile_010": [0, 0], "quartile_025": [0, 0], "median": [0.0, 0], "quartile_075": [980, 1137], "quartile_090": [2941, 3372], "max": [10000, 10000]}}, "2020-03-16": {"frequencies": ["none", "none"], "statistics": {"mean": [535.7115524781341, 320.78674948240166], "mode": [0, 0], "median": [0.0, 117], "variance": [873427.2765422951, 140802.9772514454], "n_tot": [5488, 5488], "non_zeroes": [5488, 483], "zeroes": [0, 5005]}, "box_plot": {"min": [0, 0], "quartile_010": [0, 0], "quartile_025": [0, 0], "median": [0.0, 117], "quartile_075": [823, 549], "quartile_090": [1647, 901], "max": [9372, 1137]}}, "2020-03-23": {"frequencies": ["none", "none"], "statistics": {"mean": [559.3839285714286, 281.23759623609925], "mode": [0, 0], "median": [0.0, 0.0], "variance": [1894764.3717992527, 573971.401289964], "n_tot": [5488, 5488], "non_zeroes": [5488, 4676], "zeroes": [0, 812]}, "box_plot": {"min": [0, 0], "quartile_010": [0, 0], "quartile_025": [0, 0], "median": [0.0, 0.0], "quartile_075": [352, 196], "quartile_090": [1803, 784], "max": [10000, 8666]}}, "2020-03-30": {"frequencies": ["none", "none"], "statistics": {"mean": [78.9422831632653, 78.2563775510204], "mode": [0, 0], "median": [0.0, 0.0], "variance": [38224.52202655584, 21391.990814264882], "n_tot": [5488, 5488], "non_zeroes": [3136, 2352], "zeroes": [2352, 3136]}, "box_plot": {"min": [0, 0], "quartile_010": [0, 0], "quartile_025": [0, 0], "median": [0.0, 0.0], "quartile_075": [78, 117], "quartile_090": [196, 196], "max": [1176, 705]}}, "2020-04-06": {"frequencies": ["none", "none"], "statistics": {"mean": [371.0737244897959, 105.42920918367346], "mode": [0, 0], "median": [0.0, 0.0], "variance": [1224753.353328304, 27070.91109551476], "n_tot": [5488, 5488], "non_zeroes": [3920, 3136], "zeroes": [1568, 2352]}, "box_plot": {"min": [0, 0], "quartile_010": [0, 0], "quartile_025": [0, 0], "median": [0.0, 0.0], "quartile_075": [235, 196], "quartile_090": [745, 274], "max": [10000, 823]}}, "2020-04-13": {"frequencies": ["none", "none"], "statistics": {"mean": [286.54566326530613, 144.2826420890937], "mode": [0, 0], "median": [0.0, 0.0], "variance": [322618.8848752936, 111522.10913736449], "n_tot": [5488, 5488], "non_zeroes": [3920, 1302], "zeroes": [1568, 4186]}, "box_plot": {"min": [0, 0], "quartile_010": [0, 0], "quartile_025": [0, 0], "median": [0.0, 0.0], "quartile_075": [274, 196], "quartile_090": [1019, 274], "max": [4509, 2000]}}, "2020-04-20": {"frequencies": ["none", "none"], "statistics": {"mean": [720.7410714285714, 387.5854591836735], "mode": [0, 0], "median": [0.0, 0.0], "variance": [1825645.0951786092, 458921.09613567655], "n_tot": [5488, 5488], "non_zeroes": [4704, 784], "zeroes": [784, 4704]}, "box_plot": {"min": [0, 0], "quartile_010": [0, 0], "quartile_025": [0, 0], "median": [0.0, 0.0], "quartile_075": [1019, 549], "quartile_090": [2235, 862], "max": [10000, 2745]}}, "2020-04-27": {"frequencies": ["none", "none"], "statistics": {"mean": [346.71629008746356, 263.1921768707483], "mode": [0, 0], "median": [0.0, 0.0], "variance": [382129.49284921924, 145405.26377543787], "n_tot": [5488, 5488], "non_zeroes": [5488, 2352], "zeroes": [0, 3136]}, "box_plot": {"min": [0, 0], "quartile_010": [0, 0], "quartile_025": [0, 0], "median": [0.0, 0.0], "quartile_075": [470, 470], "quartile_090": [1294, 941], "max": [4823, 1490]}}, "2020-05-04": {"frequencies": ["none", "none"], "statistics": {"mean": [385.21173469387753, 417.9905594405594], "mode": [0, 0], "median": [0.0, 0.0], "variance": [788836.6425772401, 945689.0474799249], "n_tot": [5488, 5488], "non_zeroes": [3920, 2860], "zeroes": [1568, 2628]}, "box_plot": {"min": [0, 0], "quartile_010": [0, 0], "quartile_025": [0, 0], "median": [0.0, 0.0], "quartile_075": [509, 509], "quartile_090": [1215, 1215], "max": [7803, 7803]}}, "2020-05-11": {"frequencies": ["none", "none"], "statistics": {"mean": [383.69497084548107, 558.4400510204082], "mode": [0, 0], "median": [117.0, 274.0], "variance": [421504.7379954793, 765499.0640353865], "n_tot": [5488, 5488], "non_zeroes": [5488, 2352], "zeroes": [0, 3136]}, "box_plot": {"min": [0, 0], "quartile_010": [0, 0], "quartile_025": [0, 0], "median": [117.0, 274.0], "quartile_075": [588, 784], "quartile_090": [980, 1333], "max": [8000, 8000]}}, "2020-05-18": {"frequencies": ["none", "none"], "statistics": {"mean": [286.2042638483965, 382.3012757605496], "mode": [0, 0], "median": [0.0, 39.0], "variance": [325902.5281611493, 591337.8659875714], "n_tot": [5488, 5488], "non_zeroes": [5488, 2038], "zeroes": [0, 3450]}, "box_plot": {"min": [0, 0], "quartile_010": [0, 0], "quartile_025": [0, 0], "median": [0.0, 39.0], "quartile_075": [392, 470], "quartile_090": [862, 1098], "max": [7450, 7450]}}, "2020-05-25": {"frequencies": ["none", "none"], "statistics": {"mean": [313.61078717201167, 296.5054487179487], "mode": [0, 0], "median": [0.0, 0.0], "variance": [223080.5818555494, 260414.12244545427], "n_tot": [5488, 5488], "non_zeroes": [5488, 3120], "zeroes": [0, 2368]}, "box_plot": {"min": [0, 0], "quartile_010": [0, 0], "quartile_025": [0, 0], "median": [0.0, 0.0], "quartile_075": [509, 392], "quartile_090": [1019, 1137], "max": [4235, 4235]}}, "2020-06-01": {"frequencies": ["none", "none"], "statistics": {"mean": [493.7130102040816, 343.73660714285717], "mode": [0, 0], "median": [196.0, 117.0], "variance": [633070.1507182561, 251960.28913476874], "n_tot": [5488, 5488], "non_zeroes": [5488, 3136], "zeroes": [0, 2352]}, "box_plot": {"min": [0, 0], "quartile_010": [0, 0], "quartile_025": [0, 0], "median": [196.0, 117.0], "quartile_075": [705, 470], "quartile_090": [1490, 941], "max": [6431, 2588]}}, "2020-06-08": {"frequencies": ["none", "none"], "statistics": {"mean": [561.1339285714286, 517.3974025974026], "mode": [0, 0], "median": [39.0, 39.0], "variance": [873589.9538112812, 615557.8160175035], "n_tot": [5488, 5488], "non_zeroes": [5488, 2310], "zeroes": [0, 3178]}, "box_plot": {"min": [0, 0], "quartile_010": [0, 0], "quartile_025": [0, 0], "median": [39.0, 39.0], "quartile_075": [745, 784], "quartile_090": [1921, 1843], "max": [5960, 3098]}}, "2020-06-15": {"frequencies": ["none", "none"], "statistics": {"mean": [1349.2370626822158, 2211.1716839134524], "mode": [0, 0], "median": [0.0, 1803.0], "variance": [4631723.822230991, 6347215.242510763], "n_tot": [5488, 5488], "non_zeroes": [5488, 2126], "zeroes": [0, 3362]}, "box_plot": {"min": [0, 0], "quartile_010": [0, 0], "quartile_025": [0, 0], "median": [0.0, 1803.0], "quartile_075": [2078, 3372], "quartile_090": [3960, 5882], "max": [10000, 10000]}}, "2020-06-22": {"frequencies": ["none", "none"], "statistics": {"mean": [880.1816690962099, 1122.7031195233087], "mode": [0, 0], "median": [0.0, 0], "variance": [2117164.617072337, 2795789.945842299], "n_tot": [5488, 5488], "non_zeroes": [5488, 2853], "zeroes": [0, 2635]}, "box_plot": {"min": [0, 0], "quartile_010": [0, 0], "quartile_025": [0, 0], "median": [0.0, 0], "quartile_075": [1333, 2156], "quartile_090": [2980, 3490], "max": [7294, 7294]}}, "2020-06-29": {"frequencies": ["none", "none"], "statistics": {"mean": [451.3573250728863, 257.3817131203263], "mode": [0, 0], "median": [78.0, 39.0], "variance": [669612.2712384786, 158312.05723773065], "n_tot": [5488, 5488], "non_zeroes": [5488, 2942], "zeroes": [0, 2546]}, "box_plot": {"min": [0, 0], "quartile_010": [0, 0], "quartile_025": [0, 0], "median": [78.0, 39.0], "quartile_075": [470, 392], "quartile_090": [1333, 901], "max": [5529, 1764]}}, "2020-07-06": {"frequencies": ["none", "none"], "statistics": {"mean": [383.1752915451895, 236.79504814305363], "mode": [0, 0], "median": [39.0, 0], "variance": [410742.7718916591, 191524.54058150592], "n_tot": [5488, 5488], "non_zeroes": [5488, 727], "zeroes": [0, 4761]}, "box_plot": {"min": [0, 0], "quartile_010": [0, 0], "quartile_025": [0, 0], "median": [39.0, 0], "quartile_075": [470, 274], "quartile_090": [1372, 823], "max": [3450, 2156]}}, "2020-07-13": {"frequencies": ["none", "none"], "statistics": {"mean": [1215.7461734693877, -1], "mode": [0, -1], "median": [313.0, -1], "variance": [4179876.335232302, -1], "n_tot": [5488, 5488], "non_zeroes": [5488, 0], "zeroes": [0, 5488]}, "box_plot": {"min": [0, -1], "quartile_010": [0, -1], "quartile_025": [0, -1], "median": [313.0, -1], "quartile_075": [1647, -1], "quartile_090": [3411, -1], "max": [10000, -1]}}, "2020-07-20": {"frequencies": ["none", "none"], "statistics": {"mean": [481.0878279883382, 733.4], "mode": [0, 0], "median": [39.0, 0], "variance": [1276380.6811858774, 1322572.30625], "n_tot": [5488, 5488], "non_zeroes": [5488, 65], "zeroes": [0, 5423]}, "box_plot": {"min": [0, 0], "quartile_010": [0, 0], "quartile_025": [0, 0], "median": [39.0, 0], "quartile_075": [431, 2509], "quartile_090": [1686, 2509], "max": [9333, 2509]}}, "2020-07-27": {"frequencies": ["none", "none"], "statistics": {"mean": [729.3292638483965, -1], "mode": [0, -1], "median": [39.0, -1], "variance": [2428336.249320253, -1], "n_tot": [5488, 5488], "non_zeroes": [5488, 0], "zeroes": [0, 5488]}, "box_plot": {"min": [0, -1], "quartile_010": [0, -1], "quartile_025": [0, -1], "median": [39.0, -1], "quartile_075": [588, -1], "quartile_090": [2470, -1], "max": [10000, -1]}}, "2020-08-03": {"frequencies": ["none", "none"], "statistics": {"mean": [1463.2990160349855, -1], "mode": [0, -1], "median": [39.0, -1], "variance": [6435392.656153578, -1], "n_tot": [5488, 5488], "non_zeroes": [5488, 0], "zeroes": [0, 5488]}, "box_plot": {"min": [0, -1], "quartile_010": [0, -1], "quartile_025": [0, -1], "median": [39.0, -1], "quartile_075": [1803, -1], "quartile_090": [4941, -1], "max": [10000, -1]}}, "2020-08-10": {"frequencies": ["none", "none"], "statistics": {"mean": [810.1175291545189, -1], "mode": [0, -1], "median": [78.0, -1], "variance": [2084203.0003997989, -1], "n_tot": [5488, 5488], "non_zeroes": [5488, 0], "zeroes": [0, 5488]}, "box_plot": {"min": [0, -1], "quartile_010": [0, -1], "quartile_025": [0, -1], "median": [78.0, -1], "quartile_075": [784, -1], "quartile_090": [2470, -1], "max": [10000, -1]}}, "2020-08-17": {"frequencies": ["none", "none"], "statistics": {"mean": [796.1652208201892, 300.0547368421053], "mode": [0, 0], "median": [0.0, 274], "variance": [2916894.1616140706, 85915.38096380192], "n_tot": [5488, 5488], "non_zeroes": [5072, 475], "zeroes": [416, 5013]}, "box_plot": {"min": [0, 0], "quartile_010": [0, 0], "quartile_025": [0, 0], "median": [0.0, 274], "quartile_075": [705, 392], "quartile_090": [2745, 705], "max": [10000, 1058]}}, "2020-08-24": {"frequencies": ["none", "none"], "statistics": {"mean": [456.52332361516034, 309.61494505494505], "mode": [0, 0], "median": [0.0, 196], "variance": [2408717.645528445, 152508.43829897454], "n_tot": [5488, 5488], "non_zeroes": [5488, 2275], "zeroes": [0, 3213]}, "box_plot": {"min": [0, 0], "quartile_010": [0, 0], "quartile_025": [0, 0], "median": [0.0, 196], "quartile_075": [235, 509], "quartile_090": [862, 980], "max": [10000, 1764]}}, "2020-08-31": {"frequencies": ["none", "none"], "statistics": {"mean": [191.9560860058309, 275.2647374062165], "mode": [0, 0], "median": [0.0, 0.0], "variance": [108451.11070106203, 147815.54703470314], "n_tot": [5488, 5488], "non_zeroes": [5488, 1866], "zeroes": [0, 3622]}, "box_plot": {"min": [0, 0], "quartile_010": [0, 0], "quartile_025": [0, 0], "median": [0.0, 0.0], "quartile_075": [274, 470], "quartile_090": [627, 823], "max": [1725, 1725]}}, "2020-09-07": {"frequencies": ["none", "none"], "statistics": {"mean": [681.9560860058309, 193.53194351042367], "mode": [0, 0], "median": [78.0, 78], "variance": [3264136.3948271787, 68100.49410005604], "n_tot": [5488, 5488], "non_zeroes": [5488, 1487], "zeroes": [0, 4001]}, "box_plot": {"min": [0, 0], "quartile_010": [0, 0], "quartile_025": [0, 0], "median": [78.0, 78], "quartile_075": [431, 313], "quartile_090": [1411, 588], "max": [10000, 1058]}}, "2020-09-14": {"frequencies": ["none", "none"], "statistics": {"mean": [687.7536443148688, 377.1823056300268], "mode": [0, 0], "median": [117.0, 117.0], "variance": [2019234.952237491, 260550.4736787228], "n_tot": [5488, 5488], "non_zeroes": [5488, 2238], "zeroes": [0, 3250]}, "box_plot": {"min": [0, 0], "quartile_010": [0, 0], "quartile_025": [0, 0], "median": [117.0, 117.0], "quartile_075": [862, 509], "quartile_090": [1607, 980], "max": [10000, 2549]}}, "2020-09-21": {"frequencies": ["none", "none"], "statistics": {"mean": [1136.6144314868804, -1], "mode": [0, -1], "median": [196.0, -1], "variance": [3216059.4747834927, -1], "n_tot": [5488, 5488], "non_zeroes": [5488, 0], "zeroes": [0, 5488]}, "box_plot": {"min": [0, -1], "quartile_010": [0, -1], "quartile_025": [0, -1], "median": [196.0, -1], "quartile_075": [1529, -1], "quartile_090": [4117, -1], "max": [9176, -1]}}, "2020-09-28": {"frequencies": ["none", "none"], "statistics": {"mean": [991.6235422740525, -1], "mode": [0, -1], "median": [196.0, -1], "variance": [3155871.3155163727, -1], "n_tot": [5488, 5488], "non_zeroes": [5488, 0], "zeroes": [0, 5488]}, "box_plot": {"min": [0, -1], "quartile_010": [0, -1], "quartile_025": [0, -1], "median": [196.0, -1], "quartile_075": [1098, -1], "quartile_090": [2705, -1], "max": [10000, -1]}}, "2020-10-05": {"frequencies": ["none", "none"], "statistics": {"mean": [400.33217930029156, -1], "mode": [0, -1], "median": [0.0, -1], "variance": [523100.27290634875, -1], "n_tot": [5488, 5488], "non_zeroes": [5488, 0], "zeroes": [0, 5488]}, "box_plot": {"min": [0, -1], "quartile_010": [0, -1], "quartile_025": [0, -1], "median": [0.0, -1], "quartile_075": [509, -1], "quartile_090": [1450, -1], "max": [4705, -1]}}, "2020-10-12": {"frequencies": ["none", "none"], "statistics": {"mean": [615.3442055393587, -1], "mode": [0, -1], "median": [0.0, -1], "variance": [1905528.4984136568, -1], "n_tot": [5488, 5488], "non_zeroes": [5488, 0], "zeroes": [0, 5488]}, "box_plot": {"min": [0, -1], "quartile_010": [0, -1], "quartile_025": [0, -1], "median": [0.0, -1], "quartile_075": [588, -1], "quartile_090": [2078, -1], "max": [10000, -1]}}, "2020-10-19": {"frequencies": ["none", "none"], "statistics": {"mean": [783.4544447521462, -1], "mode": [0, -1], "median": [0, -1], "variance": [4166718.642453231, -1], "n_tot": [5488, 5488], "non_zeroes": [3611, 0], "zeroes": [1877, 5488]}, "box_plot": {"min": [0, -1], "quartile_010": [0, -1], "quartile_025": [0, -1], "median": [0, -1], "quartile_075": [274, -1], "quartile_090": [3490, -1], "max": [10000, -1]}}, "2020-10-26": {"frequencies": ["none", "none"], "statistics": {"mean": [752.8, -1], "mode": [0, -1], "median": [0, -1], "variance": [1062577.2, -1], "n_tot": [5488, 5488], "non_zeroes": [5, 0], "zeroes": [5483, 5488]}, "box_plot": {"min": [0, -1], "quartile_010": [0, -1], "quartile_025": [0, -1], "median": [0, -1], "quartile_075": [1882, -1], "quartile_090": [1882, -1], "max": [1882, -1]}}, "2020-11-02": {"frequencies": ["none", "none"], "statistics": {"mean": [-1, -1], "mode": [-1, -1], "median": [-1, -1], "variance": [-1, -1], "n_tot": [5488, 5488], "non_zeroes": [0, 0], "zeroes": [5488, 5488]}, "box_plot": {"min": [-1, -1], "quartile_010": [-1, -1], "quartile_025": [-1, -1], "median": [-1, -1], "quartile_075": [-1, -1], "quartile_090": [-1, -1], "max": [-1, -1]}}, "2020-11-09": {"frequencies": ["none", "none"], "statistics": {"mean": [-1, -1], "mode": [-1, -1], "median": [-1, -1], "variance": [-1, -1], "n_tot": [5488, 5488], "non_zeroes": [0, 0], "zeroes": [5488, 5488]}, "box_plot": {"min": [-1, -1], "quartile_010": [-1, -1], "quartile_025": [-1, -1], "median": [-1, -1], "quartile_075": [-1, -1], "quartile_090": [-1, -1], "max": [-1, -1]}}, "2020-11-16": {"frequencies": ["none", "none"], "statistics": {"mean": [-1, -1], "mode": [-1, -1], "median": [-1, -1], "variance": [-1, -1], "n_tot": [5488, 5488], "non_zeroes": [0, 0], "zeroes": [5488, 5488]}, "box_plot": {"min": [-1, -1], "quartile_010": [-1, -1], "quartile_025": [-1, -1], "median": [-1, -1], "quartile_075": [-1, -1], "quartile_090": [-1, -1], "max": [-1, -1]}}, "2020-11-23": {"frequencies": ["none", "none"], "statistics": {"mean": [-1, -1], "mode": [-1, -1], "median": [-1, -1], "variance": [-1, -1], "n_tot": [5488, 5488], "non_zeroes": [0, 0], "zeroes": [5488, 5488]}, "box_plot": {"min": [-1, -1], "quartile_010": [-1, -1], "quartile_025": [-1, -1], "median": [-1, -1], "quartile_075": [-1, -1], "quartile_090": [-1, -1], "max": [-1, -1]}}, "2020-11-30": {"frequencies": ["none", "none"], "statistics": {"mean": [-1, -1], "mode": [-1, -1], "median": [-1, -1], "variance": [-1, -1], "n_tot": [5488, 5488], "non_zeroes": [0, 0], "zeroes": [5488, 5488]}, "box_plot": {"min": [-1, -1], "quartile_010": [-1, -1], "quartile_025": [-1, -1], "median": [-1, -1], "quartile_075": [-1, -1], "quartile_090": [-1, -1], "max": [-1, -1]}}, "2020-12-07": {"frequencies": ["none", "none"], "statistics": {"mean": [-1, -1], "mode": [-1, -1], "median": [-1, -1], "variance": [-1, -1], "n_tot": [5488, 5488], "non_zeroes": [0, 0], "zeroes": [5488, 5488]}, "box_plot": {"min": [-1, -1], "quartile_010": [-1, -1], "quartile_025": [-1, -1], "median": [-1, -1], "quartile_075": [-1, -1], "quartile_090": [-1, -1], "max": [-1, -1]}}, "2020-12-14": {"frequencies": ["none", "none"], "statistics": {"mean": [-1, -1], "mode": [-1, -1], "median": [-1, -1], "variance": [-1, -1], "n_tot": [5488, 5488], "non_zeroes": [0, 0], "zeroes": [5488, 5488]}, "box_plot": {"min": [-1, -1], "quartile_010": [-1, -1], "quartile_025": [-1, -1], "median": [-1, -1], "quartile_075": [-1, -1], "quartile_090": [-1, -1], "max": [-1, -1]}}, "2020-12-21": {"frequencies": ["none", "none"], "statistics": {"mean": [-1, -1], "mode": [-1, -1], "median": [-1, -1], "variance": [-1, -1], "n_tot": [5488, 5488], "non_zeroes": [0, 0], "zeroes": [5488, 5488]}, "box_plot": {"min": [-1, -1], "quartile_010": [-1, -1], "quartile_025": [-1, -1], "median": [-1, -1], "quartile_075": [-1, -1], "quartile_090": [-1, -1], "max": [-1, -1]}}, "2020-12-28": {"frequencies": ["none", "none"], "statistics": {"mean": [-1, -1], "mode": [-1, -1], "median": [-1, -1], "variance": [-1, -1], "n_tot": [5488, 5488], "non_zeroes": [0, 0], "zeroes": [5488, 5488]}, "box_plot": {"min": [-1, -1], "quartile_010": [-1, -1], "quartile_025": [-1, -1], "median": [-1, -1], "quartile_075": [-1, -1], "quartile_090": [-1, -1], "max": [-1, -1]}}, "2021-01-04": {"frequencies": ["none", "none"], "statistics": {"mean": [-1, -1], "mode": [-1, -1], "median": [-1, -1], "variance": [-1, -1], "n_tot": [5488, 5488], "non_zeroes": [0, 0], "zeroes": [5488, 5488]}, "box_plot": {"min": [-1, -1], "quartile_010": [-1, -1], "quartile_025": [-1, -1], "median": [-1, -1], "quartile_075": [-1, -1], "quartile_090": [-1, -1], "max": [-1, -1]}}, "2021-01-11": {"frequencies": ["none", "none"], "statistics": {"mean": [-1, -1], "mode": [-1, -1], "median": [-1, -1], "variance": [-1, -1], "n_tot": [5488, 5488], "non_zeroes": [0, 0], "zeroes": [5488, 5488]}, "box_plot": {"min": [-1, -1], "quartile_010": [-1, -1], "quartile_025": [-1, -1], "median": [-1, -1], "quartile_075": [-1, -1], "quartile_090": [-1, -1], "max": [-1, -1]}}, "2021-01-18": {"frequencies": ["none", "none"], "statistics": {"mean": [-1, -1], "mode": [-1, -1], "median": [-1, -1], "variance": [-1, -1], "n_tot": [5488, 5488], "non_zeroes": [0, 0], "zeroes": [5488, 5488]}, "box_plot": {"min": [-1, -1], "quartile_010": [-1, -1], "quartile_025": [-1, -1], "median": [-1, -1], "quartile_075": [-1, -1], "quartile_090": [-1, -1], "max": [-1, -1]}}, "2021-01-25": {"frequencies": ["none", "none"], "statistics": {"mean": [-1, -1], "mode": [-1, -1], "median": [-1, -1], "variance": [-1, -1], "n_tot": [5488, 5488], "non_zeroes": [0, 0], "zeroes": [5488, 5488]}, "box_plot": {"min": [-1, -1], "quartile_010": [-1, -1], "quartile_025": [-1, -1], "median": [-1, -1], "quartile_075": [-1, -1], "quartile_090": [-1, -1], "max": [-1, -1]}}, "2021-02-01": {"frequencies": ["none", "none"], "statistics": {"mean": [-1, -1], "mode": [-1, -1], "median": [-1, -1], "variance": [-1, -1], "n_tot": [5488, 5488], "non_zeroes": [0, 0], "zeroes": [5488, 5488]}, "box_plot": {"min": [-1, -1], "quartile_010": [-1, -1], "quartile_025": [-1, -1], "median": [-1, -1], "quartile_075": [-1, -1], "quartile_090": [-1, -1], "max": [-1, -1]}}, "2021-02-08": {"frequencies": ["none", "none"], "statistics": {"mean": [270.83720930232556, -1], "mode": [0, -1], "median": [0, -1], "variance": [1001323.8538205981, -1], "n_tot": [5488, 5488], "non_zeroes": [43, 0], "zeroes": [5445, 5488]}, "box_plot": {"min": [0, -1], "quartile_010": [0, -1], "quartile_025": [0, -1], "median": [0, -1], "quartile_075": [0, -1], "quartile_090": [0, -1], "max": [3882, -1]}}, "2021-02-15": {"frequencies": ["none", "none"], "statistics": {"mean": [1407.0161480897991, -1], "mode": [0, -1], "median": [0.0, -1], "variance": [9454619.517564677, -1], "n_tot": [5488, 5488], "non_zeroes": [5078, 0], "zeroes": [410, 5488]}, "box_plot": {"min": [0, -1], "quartile_010": [0, -1], "quartile_025": [0, -1], "median": [0.0, -1], "quartile_075": [0, -1], "quartile_090": [6784, -1], "max": [10000, -1]}}, "2021-02-22": {"frequencies": ["none", "none"], "statistics": {"mean": [606.5730685131196, -1], "mode": [0, -1], "median": [0.0, -1], "variance": [2924470.820976768, -1], "n_tot": [5488, 5488], "non_zeroes": [5488, 0], "zeroes": [0, 5488]}, "box_plot": {"min": [0, -1], "quartile_010": [0, -1], "quartile_025": [0, -1], "median": [0.0, -1], "quartile_075": [0, -1], "quartile_090": [1882, -1], "max": [10000, -1]}}, "2021-03-01": {"frequencies": ["none", "none"], "statistics": {"mean": [844.094752186589, -1], "mode": [0, -1], "median": [0.0, -1], "variance": [4004527.852146685, -1], "n_tot": [5488, 5488], "non_zeroes": [5488, 0], "zeroes": [0, 5488]}, "box_plot": {"min": [0, -1], "quartile_010": [0, -1], "quartile_025": [0, -1], "median": [0.0, -1], "quartile_075": [705, -1], "quartile_090": [2666, -1], "max": [10000, -1]}}, "2021-03-08": {"frequencies": ["none", "none"], "statistics": {"mean": [387.832361516035, -1], "mode": [0, -1], "median": [0.0, -1], "variance": [1413692.9742614534, -1], "n_tot": [5488, 5488], "non_zeroes": [5488, 0], "zeroes": [0, 5488]}, "box_plot": {"min": [0, -1], "quartile_010": [0, -1], "quartile_025": [0, -1], "median": [0.0, -1], "quartile_075": [352, -1], "quartile_090": [901, -1], "max": [10000, -1]}}, "2021-03-15": {"frequencies": ["none", "none"], "statistics": {"mean": [337.38429300291546, 118.9304347826087], "mode": [0, 0], "median": [0.0, 0.0], "variance": [701745.658925835, 35006.807366622364], "n_tot": [5488, 5488], "non_zeroes": [5488, 230], "zeroes": [0, 5258]}, "box_plot": {"min": [0, 0], "quartile_010": [0, 0], "quartile_025": [0, 0], "median": [0.0, 0.0], "quartile_075": [352, 392], "quartile_090": [862, 431], "max": [7647, 431]}}, "2021-03-22": {"frequencies": ["none", "none"], "statistics": {"mean": [391.0140306122449, 336.4711425206125], "mode": [0, 0], "median": [0.0, 39], "variance": [554510.2959576532, 295608.39097050915], "n_tot": [5488, 5488], "non_zeroes": [5488, 849], "zeroes": [0, 4639]}, "box_plot": {"min": [0, 0], "quartile_010": [0, 0], "quartile_025": [0, 0], "median": [0.0, 39], "quartile_075": [549, 549], "quartile_090": [1294, 941], "max": [5843, 2196]}}, "2021-03-29": {"frequencies": ["none", "none"], "statistics": {"mean": [572.384203480589, 636.9498785603886], "mode": [0, 0], "median": [117, 235], "variance": [880486.3544635057, 950222.0922311028], "n_tot": [5488, 5488], "non_zeroes": [5229, 4529], "zeroes": [259, 959]}, "box_plot": {"min": [0, 0], "quartile_010": [0, 0], "quartile_025": [0, 0], "median": [117, 235], "quartile_075": [705, 862], "quartile_090": [1568, 1568], "max": [6627, 6627]}}, "2021-04-05": {"frequencies": ["none", "none"], "statistics": {"mean": [223.56675170068027, 168.35721169290073], "mode": [0, 0], "median": [0.0, 0], "variance": [591610.010002119, 75001.4571917087], "n_tot": [5488, 5488], "non_zeroes": [4704, 3113], "zeroes": [784, 2375]}, "box_plot": {"min": [0, 0], "quartile_010": [0, 0], "quartile_025": [0, 0], "median": [0.0, 0], "quartile_075": [196, 313], "quartile_090": [470, 549], "max": [10000, 1254]}}, "2021-04-12": {"frequencies": ["none", "none"], "statistics": {"mean": [406.73496055226826, 17.205882352941178], "mode": [0, 0], "median": [0.0, 0.0], "variance": [1222984.1864568663, 1729.764705882353], "n_tot": [5488, 5488], "non_zeroes": [4056, 136], "zeroes": [1432, 5352]}, "box_plot": {"min": [0, 0], "quartile_010": [0, 0], "quartile_025": [0, 0], "median": [0.0, 0.0], "quartile_075": [0, 0], "quartile_090": [1333, 117], "max": [10000, 117]}}, "2021-04-19": {"frequencies": ["none", "none"], "statistics": {"mean": [527.4748542274052, 52.933673469387756], "mode": [0, 0], "median": [0.0, 0.0], "variance": [1910288.1407927617, 7742.682696066931], "n_tot": [5488, 5488], "non_zeroes": [5488, 784], "zeroes": [0, 4704]}, "box_plot": {"min": [0, 0], "quartile_010": [0, 0], "quartile_025": [0, 0], "median": [0.0, 0.0], "quartile_075": [156, 78], "quartile_090": [1686, 196], "max": [10000, 313]}}, "2021-04-26": {"frequencies": ["none", "none"], "statistics": {"mean": [885.0830903790087, -1], "mode": [0, -1], "median": [0.0, -1], "variance": [3546278.0127776177, -1], "n_tot": [5488, 5488], "non_zeroes": [5488, 0], "zeroes": [0, 5488]}, "box_plot": {"min": [0, -1], "quartile_010": [0, -1], "quartile_025": [0, -1], "median": [0.0, -1], "quartile_075": [823, -1], "quartile_090": [2823, -1], "max": [10000, -1]}}, "2021-05-03": {"frequencies": ["none", "none"], "statistics": {"mean": [457.12044460641397, -1], "mode": [0, -1], "median": [0.0, -1], "variance": [698429.1065037571, -1], "n_tot": [5488, 5488], "non_zeroes": [5488, 0], "zeroes": [0, 5488]}, "box_plot": {"min": [0, -1], "quartile_010": [0, -1], "quartile_025": [0, -1], "median": [0.0, -1], "quartile_075": [549, -1], "quartile_090": [1647, -1], "max": [4666, -1]}}, "2021-05-10": {"frequencies": ["none", "none"], "statistics": {"mean": [519.6255466472303, 391.45787545787545], "mode": [0, 0], "median": [0.0, 549], "variance": [1199171.500910946, 147199.63149105798], "n_tot": [5488, 5488], "non_zeroes": [5488, 273], "zeroes": [0, 5215]}, "box_plot": {"min": [0, 0], "quartile_010": [0, 0], "quartile_025": [0, 0], "median": [0.0, 549], "quartile_075": [588, 588], "quartile_090": [1607, 980], "max": [8666, 980]}}, "2021-05-17": {"frequencies": ["none", "none"], "statistics": {"mean": [339.03844752186586, 0], "mode": [0, 0], "median": [0.0, 0], "variance": [738219.6655526832, 0], "n_tot": [5488, 5488], "non_zeroes": [5488, 69], "zeroes": [0, 5419]}, "box_plot": {"min": [0, 0], "quartile_010": [0, 0], "quartile_025": [0, 0], "median": [0.0, 0], "quartile_075": [235, 0], "quartile_090": [1098, 0], "max": [10000, 0]}}, "2021-05-24": {"frequencies": ["none", "none"], "statistics": {"mean": [408.59620991253644, 401], "mode": [0, 0], "median": [0.0, 156], "variance": [534021.6069256727, 529414.641025641], "n_tot": [5488, 5488], "non_zeroes": [5488, 391], "zeroes": [0, 5097]}, "box_plot": {"min": [0, 0], "quartile_010": [0, 0], "quartile_025": [0, 0], "median": [0.0, 156], "quartile_075": [588, 274], "quartile_090": [1411, 1529], "max": [10000, 10000]}}, "2021-05-31": {"frequencies": ["none", "none"], "statistics": {"mean": [599.4336734693877, -1], "mode": [0, -1], "median": [0.0, -1], "variance": [1775254.8423286208, -1], "n_tot": [5488, 5488], "non_zeroes": [5488, 0], "zeroes": [0, 5488]}, "box_plot": {"min": [0, -1], "quartile_010": [0, -1], "quartile_025": [0, -1], "median": [0.0, -1], "quartile_075": [627, -1], "quartile_090": [2039, -1], "max": [8980, -1]}}, "2021-06-07": {"frequencies": ["none", "none"], "statistics": {"mean": [1755.9187317784256, 342.41818181818184], "mode": [0, 509], "median": [78.0, 509], "variance": [7634491.252734532, 58096.951515151515], "n_tot": [5488, 5488], "non_zeroes": [5488, 55], "zeroes": [0, 5433]}, "box_plot": {"min": [0, 0], "quartile_010": [0, 0], "quartile_025": [0, 0], "median": [78.0, 509], "quartile_075": [2470, 509], "quartile_090": [5960, 509], "max": [10000, 509]}}, "2021-06-14": {"frequencies": ["none", "none"], "statistics": {"mean": [1702.1820335276968, 2155.3441176470587], "mode": [0, 0], "median": [0.0, 1294.0], "variance": [7412311.739228814, 4289959.81928683], "n_tot": [5488, 5488], "non_zeroes": [5488, 340], "zeroes": [0, 5148]}, "box_plot": {"min": [0, 0], "quartile_010": [0, 0], "quartile_025": [0, 392], "median": [0.0, 1294.0], "quartile_075": [2313, 3803], "quartile_090": [6078, 5372], "max": [10000, 6196]}}, "2021-06-21": {"frequencies": ["none", "none"], "statistics": {"mean": [1233.151967930029, 612.328173374613], "mode": [0, 0], "median": [0.0, 235], "variance": [5973895.37147052, 573413.5565640444], "n_tot": [5488, 5488], "non_zeroes": [5488, 323], "zeroes": [0, 5165]}, "box_plot": {"min": [0, 0], "quartile_010": [0, 0], "quartile_025": [0, 0], "median": [0.0, 235], "quartile_075": [1058, 823], "quartile_090": [3529, 2117], "max": [10000, 2705]}}, "2021-06-28": {"frequencies": ["none", "none"], "statistics": {"mean": [629.052113702624, 706.1735849056604], "mode": [0, 0], "median": [0.0, 0], "variance": [1899230.9132669, 1102262.6212692966], "n_tot": [5488, 5488], "non_zeroes": [5488, 265], "zeroes": [0, 5223]}, "box_plot": {"min": [0, 0], "quartile_010": [0, 0], "quartile_025": [0, 0], "median": [0.0, 0], "quartile_075": [745, 1490], "quartile_090": [2117, 2862], "max": [10000, 2862]}}, "2021-07-05": {"frequencies": ["none", "none"], "statistics": {"mean": [1759.5102040816328, 1229.1774332472007], "mode": [0, 0], "median": [176.0, 901], "variance": [9164428.772631414, 1622620.3150420268], "n_tot": [5488, 5488], "non_zeroes": [5488, 1161], "zeroes": [0, 4327]}, "box_plot": {"min": [0, 0], "quartile_010": [0, 0], "quartile_025": [0, 0], "median": [176.0, 901], "quartile_075": [1882, 1882], "quartile_090": [8156, 3803], "max": [10000, 4235]}}, "2021-07-12": {"frequencies": ["none", "none"], "statistics": {"mean": [700.7543731778426, 3764], "mode": [0, 3764], "median": [0.0, 3764.0], "variance": [1546999.4424813276, 0], "n_tot": [5488, 5488], "non_zeroes": [5488, 2], "zeroes": [0, 5486]}, "box_plot": {"min": [0, 3764], "quartile_010": [0, 3764], "quartile_025": [0, 3764], "median": [0.0, 3764.0], "quartile_075": [862, 3764], "quartile_090": [2392, 3764], "max": [6549, 3764]}}, "2021-07-19": {"frequencies": ["none", "none"], "statistics": {"mean": [1292.0167638483965, -1], "mode": [0, -1], "median": [352.0, -1], "variance": [5846741.1034185765, -1], "n_tot": [5488, 5488], "non_zeroes": [5488, 0], "zeroes": [0, 5488]}, "box_plot": {"min": [0, -1], "quartile_010": [0, -1], "quartile_025": [0, -1], "median": [352.0, -1], "quartile_075": [1333, -1], "quartile_090": [2862, -1], "max": [10000, -1]}}, "2021-07-26": {"frequencies": ["none", "none"], "statistics": {"mean": [1292.855502915452, 1411.1176470588234], "mode": [0, 1411], "median": [0.0, 1411.0], "variance": [5440234.856280993, 362156.71301247773], "n_tot": [5488, 5488], "non_zeroes": [5488, 34], "zeroes": [0, 5454]}, "box_plot": {"min": [0, 0], "quartile_010": [0, 0], "quartile_025": [0, 1411], "median": [0.0, 1411.0], "quartile_075": [1411, 1411], "quartile_090": [4901, 2117], "max": [10000, 2117]}}, "2021-08-02": {"frequencies": ["none", "none"], "statistics": {"mean": [554.9099854227405, 222.6045918367347], "mode": [0, 0], "median": [0.0, 0.0], "variance": [809935.5807422632, 119014.51267365184], "n_tot": [5488, 5488], "non_zeroes": [5488, 784], "zeroes": [0, 4704]}, "box_plot": {"min": [0, 0], "quartile_010": [0, 0], "quartile_025": [0, 0], "median": [0.0, 0.0], "quartile_075": [784, 313], "quartile_090": [1764, 627], "max": [5058, 1215]}}, "2021-08-09": {"frequencies": ["none", "none"], "statistics": {"mean": [581.2576530612245, 713.132911392405], "mode": [0, 784], "median": [0.0, 784.0], "variance": [1730214.6939454295, 260757.87394178828], "n_tot": [5488, 5488], "non_zeroes": [5488, 158], "zeroes": [0, 5330]}, "box_plot": {"min": [0, 0], "quartile_010": [0, 196], "quartile_025": [0, 274], "median": [0.0, 784.0], "quartile_075": [352, 1411], "quartile_090": [2627, 1411], "max": [6745, 1411]}}, "2021-08-16": {"frequencies": ["none", "none"], "statistics": {"mean": [575.9375114196966, 0], "mode": [0, 0], "median": [0, 0], "variance": [3046901.868535984, 0], "n_tot": [5488, 5488], "non_zeroes": [5473, 47], "zeroes": [15, 5441]}, "box_plot": {"min": [0, 0], "quartile_010": [0, 0], "quartile_025": [0, 0], "median": [0, 0], "quartile_075": [274, 0], "quartile_090": [1019, 0], "max": [10000, 0]}}, "2021-08-23": {"frequencies": ["none", "none"], "statistics": {"mean": [1512.1732871720117, 247.8483080513419], "mode": [0, 0], "median": [78.0, 196], "variance": [9414654.301476926, 94089.29939257789], "n_tot": [5488, 5488], "non_zeroes": [5488, 857], "zeroes": [0, 4631]}, "box_plot": {"min": [0, 0], "quartile_010": [0, 0], "quartile_025": [0, 0], "median": [78.0, 196], "quartile_075": [745, 392], "quartile_090": [9450, 509], "max": [10000, 1450]}}, "2021-08-30": {"frequencies": ["none", "none"], "statistics": {"mean": [268.1262755102041, -1], "mode": [0, -1], "median": [117.0, -1], "variance": [158593.1518809502, -1], "n_tot": [1568, 1568], "non_zeroes": [1568, 0], "zeroes": [0, 1568]}, "box_plot": {"min": [0, -1], "quartile_010": [0, -1], "quartile_025": [0, -1], "median": [117.0, -1], "quartile_075": [392, -1], "quartile_090": [784, -1], "max": [4392, -1]}}, "info": {"periodicity": "WEEKLY"}}